raster2stac/__init__.py
raster2stac/_version.py
raster2stac/raster2stac.py
raster2stac/rioxarray_stac.py
raster2stac-0.0.10.dist-info/licenses/LICENSE
raster2stac-0.0.10.dist-info/METADATA
raster2stac-0.0.10.dist-info/WHEEL
raster2stac-0.0.10.dist-info/top_level.txt
raster2stac-0.0.10.dist-info/RECORD
