Metadata-Version: 2.4
Name: raster2stac
Version: 0.0.10
Summary: Create valid STAC Collections, Items and Assets given already existing raster datasets
Author-email: Michele Claus <michele.claus@eurac.edu>, Lorenzo Mercurio <lorenzo.mercurio@eurac.edu>, Rufai Omowunmi Balogun <rbalogun@eurac.edu>, Suriyah Dhinakaran <sdhinakaran@eurac.edu>
Project-URL: Homepage, https://gitlab.inf.unibz.it/earth_observation_public/raster-to-stac
Project-URL: Issues, https://gitlab.inf.unibz.it/earth_observation_public/raster-to-stac/-/issues
Keywords: STAC,Metadata,Cloud-Optimized GeoTIFFs,Kerchunk,NetCDF
Classifier: Programming Language :: Python :: 3
Classifier: License :: OSI Approved :: MIT License
Classifier: Operating System :: OS Independent
Classifier: Intended Audience :: Developers
Classifier: Intended Audience :: Education
Classifier: Intended Audience :: Science/Research
Classifier: Topic :: Software Development :: Libraries :: Python Modules
Classifier: Topic :: Scientific/Engineering :: Information Analysis
Requires-Python: >=3.10
License-File: LICENSE
Requires-Dist: kerchunk==0.2.7
Requires-Dist: openeo-pg-parser-networkx
Requires-Dist: openeo-processes-dask[implementations]<=2025.9.3
Requires-Dist: rio-stac
Requires-Dist: boto3
Requires-Dist: netcdf4==1.6.5
Requires-Dist: h5netcdf
Requires-Dist: h5py
Requires-Dist: ujson
Requires-Dist: openeo
Requires-Dist: pydantic
Provides-Extra: dev
Requires-Dist: isort; extra == "dev"
Requires-Dist: ruff; extra == "dev"
Dynamic: license-file
